datasette_notebook/__init__.py
datasette_notebook/utils.py
datasette_notebook/templates/datasette_notebook/edit.html
datasette_notebook/templates/datasette_notebook/view.html
datasette_notebook-0.2a0.dist-info/METADATA
datasette_notebook-0.2a0.dist-info/WHEEL
datasette_notebook-0.2a0.dist-info/entry_points.txt
datasette_notebook-0.2a0.dist-info/top_level.txt
datasette_notebook-0.2a0.dist-info/RECORD
