Metadata-Version: 2.1
Name: datasette-notebook
Version: 0.2a0
Summary: A markdown wiki and dashboarding system for Datasette
Home-page: https://github.com/simonw/datasette-notebook
Author: Simon Willison
License: Apache License, Version 2.0
Project-URL: Issues, https://github.com/simonw/datasette-notebook/issues
Project-URL: CI, https://github.com/simonw/datasette-notebook/actions
Project-URL: Changelog, https://github.com/simonw/datasette-notebook/releases
Platform: UNKNOWN
Requires-Python: >=3.6
Requires-Dist: datasette
Requires-Dist: sqlite-utils
Requires-Dist: markdown
Requires-Dist: bleach
Provides-Extra: test
Requires-Dist: pytest ; extra == 'test'
Requires-Dist: pytest-asyncio ; extra == 'test'
